camael/__init__.py
camael/classifier_models.py
camael/load_data.py
camael/preprocessing.py
camael/regression_models.py
camael/test_nn.py
Camael-1.0.0.dist-info/LICENSE.md
Camael-1.0.0.dist-info/METADATA
Camael-1.0.0.dist-info/WHEEL
Camael-1.0.0.dist-info/top_level.txt
Camael-1.0.0.dist-info/RECORD
