Metadata-Version: 2.1
Name: Camael
Version: 1.0.0
Summary: Machine learing library
Home-page: https://github.com/CastaChick/Camael
Author: Casta46
Author-email: casta46chick@gmail.com
License: MIT
Keywords: python MachineLearning DeepLearning
Platform: UNKNOWN
Classifier: License :: OSI Approved :: MIT License
Classifier: Programming Language :: Python :: 3.7
Requires-Dist: numpy
Requires-Dist: cvxopt
